MANIFEST.in
README.md
requirements.txt
setup.py
version.txt
energonai/__init__.py
energonai/batch_mgr.py
energonai/engine.py
energonai/pipe.py
energonai/task.py
energonai/worker.py
energonai.egg-info/PKG-INFO
energonai.egg-info/SOURCES.txt
energonai.egg-info/dependency_links.txt
energonai.egg-info/entry_points.txt
energonai.egg-info/requires.txt
energonai.egg-info/top_level.txt
energonai/__pycache__/__init__.cpython-38.pyc
energonai/__pycache__/batch_mgr.cpython-38.pyc
energonai/__pycache__/engine.cpython-38.pyc
energonai/__pycache__/pipe.cpython-38.pyc
energonai/__pycache__/task.cpython-38.pyc
energonai/__pycache__/worker.cpython-38.pyc
energonai/communication/__init__.py
energonai/communication/collective.py
energonai/communication/p2p.py
energonai/communication/ring.py
energonai/communication/utils.py
energonai/communication/__pycache__/__init__.cpython-38.pyc
energonai/communication/__pycache__/collective.cpython-38.pyc
energonai/communication/__pycache__/p2p.cpython-38.pyc
energonai/communication/__pycache__/ring.cpython-38.pyc
energonai/communication/__pycache__/utils.cpython-38.pyc
energonai/kernel/__init__.py
energonai/kernel/__pycache__/__init__.cpython-38.pyc
energonai/kernel/cuda_native/__init__.py
energonai/kernel/cuda_native/layer_norm.py
energonai/kernel/cuda_native/linear_func.py
energonai/kernel/cuda_native/scale_mask_softmax.py
energonai/kernel/cuda_native/transpose_pad.py
energonai/kernel/cuda_native/__pycache__/__init__.cpython-38.pyc
energonai/kernel/cuda_native/__pycache__/transpose_pad.cpython-38.pyc
energonai/kernel/cuda_native/csrc/common.h
energonai/kernel/cuda_native/csrc/compat.h
energonai/kernel/cuda_native/csrc/get_ncclid.cpp
energonai/kernel/cuda_native/csrc/layer_norm_cuda.cpp
energonai/kernel/cuda_native/csrc/layer_norm_cuda_kernel.cu
energonai/kernel/cuda_native/csrc/linear_wrapper.cpp
energonai/kernel/cuda_native/csrc/scale_mask_softmax_kernel.cu
energonai/kernel/cuda_native/csrc/scale_mask_softmax_wrapper.cpp
energonai/kernel/cuda_native/csrc/transpose_pad_fusion_kernel.cu
energonai/kernel/cuda_native/csrc/transpose_pad_fusion_wrapper.cpp
energonai/kernel/cuda_native/csrc/type_shim.h
energonai/legacy_batch_mgr/__init__.py
