Metadata-Version: 2.1
Name: energonai
Version: 0.0.2
Summary: EnergonAI: An Inference System for Large Transformer Models
Home-page: https://github.com/hpcaitech/EnergonAI
Maintainer: Juncong Moo;Open Source Community;HPCAiTech
Maintainer-email: juncongmoo@gmail.com
License: Apache Software License 2.0
Platform: UNKNOWN
Classifier: Operating System :: POSIX :: Linux
Classifier: Programming Language :: Python :: 3
Classifier: Programming Language :: Python :: 3.7
Classifier: Programming Language :: Python :: 3.8
Classifier: Programming Language :: Python :: 3.9
Classifier: Programming Language :: Python :: 3.10
Classifier: Programming Language :: Python :: 3.11
Classifier: Programming Language :: Python :: Implementation :: CPython
Classifier: Programming Language :: Python :: Implementation :: PyPy
Classifier: Topic :: Scientific/Engineering :: Artificial Intelligence
